{"spdxVersion":"SPDX-2.3","dataLicense":"CC0-1.0","SPDXID":"SPDXRef-DOCUMENT","name":"docker.io/kubernetesui/dashboard","documentNamespace":"https://anchore.com/syft/image/docker.io/kubernetesui/dashboard-d430a69e-ab8e-4d6b-86d1-f645ede7c2ec","creationInfo":{"licenseListVersion":"3.23","creators":["Organization: Anchore, Inc","Tool: syft-0.105.0"],"created":"2024-06-28T15:05:50Z"},"packages":[{"name":"github.com/beorn7/perks","SPDXID":"SPDXRef-Package-go-module-github.com-beorn7-perks-3d9f6f257e59912c","versionInfo":"v1.0.1","supplier":"NOASSERTION","downloadLocation":"NOASSERTION","filesAnalyzed":false,"checksums":[{"algorithm":"SHA256","checksumValue":"5656ca2a735f57c6c9cdeaa86b870e2aa3ba6d8af75a0299c4ef19d7afa1b0e3"}],"sourceInfo":"acquired package info from go module information: /dashboard","licenseConcluded":"NOASSERTION","licenseDeclared":"NOASSERTION","copyrightText":"NOASSERTION","externalRefs":[{"referenceCategory":"SECURITY","referenceType":"cpe23Type","referenceLocator":"cpe:2.3:a:beorn7:perks:v1.0.1:*:*:*:*:*:*:*"},{"referenceCategory":"PACKAGE-MANAGER","referenceType":"purl","referenceLocator":"pkg:golang/github.com/beorn7/perks@v1.0.1"}]},{"name":"github.com/cespare/xxhash/v2","SPDXID":"SPDXRef-Package-go-module-github.com-cespare-xxhash-v2-72545ddab7a1cb26","versionInfo":"v2.1.1","supplier":"NOASSERTION","downloadLocation":"NOASSERTION","filesAnalyzed":false,"checksums":[{"algorithm":"SHA256","checksumValue":"e8c9d137c353efe601a54216c47b5e7c564e29300f8068e9412c6a2cd9f4faa6"}],"sourceInfo":"acquired package info from go module information: /dashboard","licenseConcluded":"NOASSERTION","licenseDeclared":"NOASSERTION","copyrightText":"NOASSERTION","externalRefs":[{"referenceCategory":"SECURITY","referenceType":"cpe23Type","referenceLocator":"cpe:2.3:a:cespare:xxhash\\/v2:v2.1.1:*:*:*:*:*:*:*"},{"referenceCategory":"PACKAGE-MANAGER","referenceType":"purl","referenceLocator":"pkg:golang/github.com/cespare/xxhash@v2.1.1#v2"}]},{"name":"github.com/davecgh/go-spew","SPDXID":"SPDXRef-Package-go-module-github.com-davecgh-go-spew-7641503dc0c87d5c","versionInfo":"v1.1.1","supplier":"NOASSERTION","downloadLocation":"NOASSERTION","filesAnalyzed":false,"checksums":[{"algorithm":"SHA256","checksumValue":"be3f63feed5baa7bc211f24ec1486d94e011aacdfeae41d8635de36164d4f7b7"}],"sourceInfo":"acquired package info from go module information: /dashboard","licenseConcluded":"NOASSERTION","licenseDeclared":"NOASSERTION","copyrightText":"NOASSERTION","externalRefs":[{"referenceCategory":"SECURITY","referenceType":"cpe23Type","referenceLocator":"cpe:2.3:a:davecgh:go-spew:v1.1.1:*:*:*:*:*:*:*"},{"referenceCategory":"SECURITY","referenceType":"cpe23Type","referenceLocator":"cpe:2.3:a:davecgh:go_spew:v1.1.1:*:*:*:*:*:*:*"},{"referenceCategory":"PACKAGE-MANAGER","referenceType":"purl","referenceLocator":"pkg:golang/github.com/davecgh/go-spew@v1.1.1"}]},{"name":"github.com/docker/distribution","SPDXID":"SPDXRef-Package-go-module-github.com-docker-distribution-08b5a9a351ef53c0","versionInfo":"v2.7.1+incompatible","supplier":"NOASSERTION","downloadLocation":"NOASSERTION","filesAnalyzed":false,"checksums":[{"algorithm":"SHA256","checksumValue":"6b99a5915ced87a5b90387ceb12dc3d843b90549ac269701f9c4652d4edc4ae8"}],"sourceInfo":"acquired package info from go module information: /dashboard","licenseConcluded":"NOASSERTION","licenseDeclared":"NOASSERTION","copyrightText":"NOASSERTION","externalRefs":[{"referenceCategory":"SECURITY","referenceType":"cpe23Type","referenceLocator":"cpe:2.3:a:docker:distribution:v2.7.1\\+incompatible:*:*:*:*:*:*:*"},{"referenceCategory":"PACKAGE-MANAGER","referenceType":"purl","referenceLocator":"pkg:golang/github.com/docker/distribution@v2.7.1+incompatible"}]},{"name":"github.com/docker/spdystream","SPDXID":"SPDXRef-Package-go-module-github.com-docker-spdystream-ae62e3f8dd60d9f2","versionInfo":"v0.0.0-20160310174837-449fdfce4d96","supplier":"NOASSERTION","downloadLocation":"NOASSERTION","filesAnalyzed":false,"checksums":[{"algorithm":"SHA256","checksumValue":"71e9f0ad2566f99ed02d257f06c9de9c039c0d7757e1c32fe303f407fe506cf8"}],"sourceInfo":"acquired package info from go module information: /dashboard","licenseConcluded":"NOASSERTION","licenseDeclared":"NOASSERTION","copyrightText":"NOASSERTION","externalRefs":[{"referenceCategory":"SECURITY","referenceType":"cpe23Type","referenceLocator":"cpe:2.3:a:docker:spdystream:v0.0.0-20160310174837-449fdfce4d96:*:*:*:*:*:*:*"},{"referenceCategory":"PACKAGE-MANAGER","referenceType":"purl","referenceLocator":"pkg:golang/github.com/docker/spdystream@v0.0.0-20160310174837-449fdfce4d96"}]},{"name":"github.com/emicklei/go-restful","SPDXID":"SPDXRef-Package-go-module-github.com-emicklei-go-restful-89713c2a779036a7","versionInfo":"v2.12.0+incompatible","supplier":"NOASSERTION","downloadLocation":"NOASSERTION","filesAnalyzed":false,"checksums":[{"algorithm":"SHA256","checksumValue":"488be84d26ec304c2e337773162acbc0a738047e955cfe4235ff86d457c956be"}],"sourceInfo":"acquired package info from go module information: /dashboard","licenseConcluded":"NOASSERTION","licenseDeclared":"NOASSERTION","copyrightText":"NOASSERTION","externalRefs":[{"referenceCategory":"SECURITY","referenceType":"cpe23Type","referenceLocator":"cpe:2.3:a:emicklei:go-restful:v2.12.0\\+incompatible:*:*:*:*:*:*:*"},{"referenceCategory":"SECURITY","referenceType":"cpe23Type","referenceLocator":"cpe:2.3:a:emicklei:go_restful:v2.12.0\\+incompatible:*:*:*:*:*:*:*"},{"referenceCategory":"PACKAGE-MANAGER","referenceType":"purl","referenceLocator":"pkg:golang/github.com/emicklei/go-restful@v2.12.0+incompatible"}]},{"name":"github.com/gogo/protobuf","SPDXID":"SPDXRef-Package-go-module-github.com-gogo-protobuf-0b988da356741366","versionInfo":"v1.3.1","supplier":"NOASSERTION","downloadLocation":"NOASSERTION","filesAnalyzed":false,"checksums":[{"algorithm":"SHA256","checksumValue":"0ea0c4715e5a79a4e674505e3cda58b29dc595c547ff621255533d41ff0f4a5b"}],"sourceInfo":"acquired package info from go module information: /dashboard","licenseConcluded":"NOASSERTION","licenseDeclared":"NOASSERTION","copyrightText":"NOASSERTION","externalRefs":[{"referenceCategory":"SECURITY","referenceType":"cpe23Type","referenceLocator":"cpe:2.3:a:gogo:protobuf:v1.3.1:*:*:*:*:*:*:*"},{"referenceCategory":"PACKAGE-MANAGER","referenceType":"purl","referenceLocator":"pkg:golang/github.com/gogo/protobuf@v1.3.1"}]},{"name":"github.com/golang/glog","SPDXID":"SPDXRef-Package-go-module-github.com-golang-glog-aa6ac801d47e0a1a","versionInfo":"v0.0.0-20160126235308-23def4e6c14b","supplier":"NOASSERTION","downloadLocation":"NOASSERTION","filesAnalyzed":false,"checksums":[{"algorithm":"SHA256","checksumValue":"54ab7169ba97664176e6963d7a47d12fa6b9f364f83f7effdf55c4b2d439a79f"}],"sourceInfo":"acquired package info from go module information: /dashboard","licenseConcluded":"NOASSERTION","licenseDeclared":"NOASSERTION","copyrightText":"NOASSERTION","externalRefs":[{"referenceCategory":"SECURITY","referenceType":"cpe23Type","referenceLocator":"cpe:2.3:a:golang:glog:v0.0.0-20160126235308-23def4e6c14b:*:*:*:*:*:*:*"},{"referenceCategory":"PACKAGE-MANAGER","referenceType":"purl","referenceLocator":"pkg:golang/github.com/golang/glog@v0.0.0-20160126235308-23def4e6c14b"}]},{"name":"github.com/golang/protobuf","SPDXID":"SPDXRef-Package-go-module-github.com-golang-protobuf-0cffbb7042aa4592","versionInfo":"v1.3.2","supplier":"NOASSERTION","downloadLocation":"NOASSERTION","filesAnalyzed":false,"checksums":[{"algorithm":"SHA256","checksumValue":"ea7b0f63386ae6445e87a408988de4e6a5b33b83c46ef6c85b673049f47feb1b"}],"sourceInfo":"acquired package info from go module information: /dashboard","licenseConcluded":"NOASSERTION","licenseDeclared":"NOASSERTION","copyrightText":"NOASSERTION","externalRefs":[{"referenceCategory":"SECURITY","referenceType":"cpe23Type","referenceLocator":"cpe:2.3:a:golang:protobuf:v1.3.2:*:*:*:*:*:*:*"},{"referenceCategory":"PACKAGE-MANAGER","referenceType":"purl","referenceLocator":"pkg:golang/github.com/golang/protobuf@v1.3.2"}]},{"name":"github.com/google/gofuzz","SPDXID":"SPDXRef-Package-go-module-github.com-google-gofuzz-6c878f23d3b6aa66","versionInfo":"v1.1.0","supplier":"NOASSERTION","downloadLocation":"NOASSERTION","filesAnalyzed":false,"checksums":[{"algorithm":"SHA256","checksumValue":"1ec6bc986d1d438ea28fc4a5d806090d4bf5a00f7f77a564fb72c6f7d39ed368"}],"sourceInfo":"acquired package info from go module information: /dashboard","licenseConcluded":"NOASSERTION","licenseDeclared":"NOASSERTION","copyrightText":"NOASSERTION","externalRefs":[{"referenceCategory":"SECURITY","referenceType":"cpe23Type","referenceLocator":"cpe:2.3:a:google:gofuzz:v1.1.0:*:*:*:*:*:*:*"},{"referenceCategory":"PACKAGE-MANAGER","referenceType":"purl","referenceLocator":"pkg:golang/github.com/google/gofuzz@v1.1.0"}]},{"name":"github.com/googleapis/gnostic","SPDXID":"SPDXRef-Package-go-module-github.com-googleapis-gnostic-2db142b4066eaacc","versionInfo":"v0.1.0","supplier":"NOASSERTION","downloadLocation":"NOASSERTION","filesAnalyzed":false,"checksums":[{"algorithm":"SHA256","checksumValue":"ad5b0f7819976d8bf821ffdcba6bb503364fc15e7cab8df786f38d5755046682"}],"sourceInfo":"acquired package info from go module information: /dashboard","licenseConcluded":"NOASSERTION","licenseDeclared":"NOASSERTION","copyrightText":"NOASSERTION","externalRefs":[{"referenceCategory":"SECURITY","referenceType":"cpe23Type","referenceLocator":"cpe:2.3:a:googleapis:gnostic:v0.1.0:*:*:*:*:*:*:*"},{"referenceCategory":"PACKAGE-MANAGER","referenceType":"purl","referenceLocator":"pkg:golang/github.com/googleapis/gnostic@v0.1.0"}]},{"name":"github.com/gorilla/websocket","SPDXID":"SPDXRef-Package-go-module-github.com-gorilla-websocket-0ea3d3cfdb811e0e","versionInfo":"v1.4.2","supplier":"NOASSERTION","downloadLocation":"NOASSERTION","filesAnalyzed":false,"checksums":[{"algorithm":"SHA256","checksumValue":"fbf4cc69361ce10162b4a271b10ed8c9edf90e45af91d2dcbc62aa33ec7451f7"}],"sourceInfo":"acquired package info from go module information: /dashboard","licenseConcluded":"NOASSERTION","licenseDeclared":"NOASSERTION","copyrightText":"NOASSERTION","externalRefs":[{"referenceCategory":"SECURITY","referenceType":"cpe23Type","referenceLocator":"cpe:2.3:a:gorilla:websocket:v1.4.2:*:*:*:*:*:*:*"},{"referenceCategory":"PACKAGE-MANAGER","referenceType":"purl","referenceLocator":"pkg:golang/github.com/gorilla/websocket@v1.4.2"}]},{"name":"github.com/imdario/mergo","SPDXID":"SPDXRef-Package-go-module-github.com-imdario-mergo-650e120315a0b2da","versionInfo":"v0.3.5","supplier":"NOASSERTION","downloadLocation":"NOASSERTION","filesAnalyzed":false,"checksums":[{"algorithm":"SHA256","checksumValue":"25ba0192c4708a20095af218255a38e807d5f88008299a5fad2cd52a3e364784"}],"sourceInfo":"acquired package info from go module information: /dashboard","licenseConcluded":"NOASSERTION","licenseDeclared":"NOASSERTION","copyrightText":"NOASSERTION","externalRefs":[{"referenceCategory":"SECURITY","referenceType":"cpe23Type","referenceLocator":"cpe:2.3:a:imdario:mergo:v0.3.5:*:*:*:*:*:*:*"},{"referenceCategory":"PACKAGE-MANAGER","referenceType":"purl","referenceLocator":"pkg:golang/github.com/imdario/mergo@v0.3.5"}]},{"name":"github.com/json-iterator/go","SPDXID":"SPDXRef-Package-go-module-github.com-json-iterator-go-fe9da05f02e8c280","versionInfo":"v1.1.9","supplier":"NOASSERTION","downloadLocation":"NOASSERTION","filesAnalyzed":false,"checksums":[{"algorithm":"SHA256","checksumValue":"f72cee77f1eddfaca0c1ab46c79e95c0266d948ff6003d794f55f6b234ae1a7b"}],"sourceInfo":"acquired package info from go module information: /dashboard","licenseConcluded":"NOASSERTION","licenseDeclared":"NOASSERTION","copyrightText":"NOASSERTION","externalRefs":[{"referenceCategory":"SECURITY","referenceType":"cpe23Type","referenceLocator":"cpe:2.3:a:json-iterator:go:v1.1.9:*:*:*:*:*:*:*"},{"referenceCategory":"SECURITY","referenceType":"cpe23Type","referenceLocator":"cpe:2.3:a:json_iterator:go:v1.1.9:*:*:*:*:*:*:*"},{"referenceCategory":"SECURITY","referenceType":"cpe23Type","referenceLocator":"cpe:2.3:a:json:go:v1.1.9:*:*:*:*:*:*:*"},{"referenceCategory":"PACKAGE-MANAGER","referenceType":"purl","referenceLocator":"pkg:golang/github.com/json-iterator/go@v1.1.9"}]},{"name":"github.com/kubernetes/dashboard","SPDXID":"SPDXRef-Package-go-module-github.com-kubernetes-dashboard-1280d10a0c0f61e1","versionInfo":"v2.0.1","supplier":"NOASSERTION","downloadLocation":"NOASSERTION","filesAnalyzed":false,"sourceInfo":"acquired package info from go module information: /dashboard","licenseConcluded":"NOASSERTION","licenseDeclared":"NOASSERTION","copyrightText":"NOASSERTION","externalRefs":[{"referenceCategory":"SECURITY","referenceType":"cpe23Type","referenceLocator":"cpe:2.3:a:kubernetes:dashboard:v2.0.1:*:*:*:*:*:*:*"},{"referenceCategory":"PACKAGE-MANAGER","referenceType":"purl","referenceLocator":"pkg:golang/github.com/kubernetes/dashboard@v2.0.1"}]},{"name":"github.com/matttproud/golang_protobuf_extensions","SPDXID":"SPDXRef-Package-go-module-github.com-matttproud-golang-protobuf-extensions-1e24a08697e46313","versionInfo":"v1.0.1","supplier":"NOASSERTION","downloadLocation":"NOASSERTION","filesAnalyzed":false,"checksums":[{"algorithm":"SHA256","checksumValue":"e21a7d8e41f184c1e4aa4ac1dc8c748de812e6cc7f464a80465b1667aa48c225"}],"sourceInfo":"acquired package info from go module information: /dashboard","licenseConcluded":"NOASSERTION","licenseDeclared":"NOASSERTION","copyrightText":"NOASSERTION","externalRefs":[{"referenceCategory":"SECURITY","referenceType":"cpe23Type","referenceLocator":"cpe:2.3:a:matttproud:golang-protobuf-extensions:v1.0.1:*:*:*:*:*:*:*"},{"referenceCategory":"SECURITY","referenceType":"cpe23Type","referenceLocator":"cpe:2.3:a:matttproud:golang_protobuf_extensions:v1.0.1:*:*:*:*:*:*:*"},{"referenceCategory":"PACKAGE-MANAGER","referenceType":"purl","referenceLocator":"pkg:golang/github.com/matttproud/golang_protobuf_extensions@v1.0.1"}]},{"name":"github.com/modern-go/concurrent","SPDXID":"SPDXRef-Package-go-module-github.com-modern-go-concurrent-438bdbeb24c38e6b","versionInfo":"v0.0.0-20180306012644-bacd9c7ef1dd","supplier":"NOASSERTION","downloadLocation":"NOASSERTION","filesAnalyzed":false,"checksums":[{"algorithm":"SHA256","checksumValue":"4d12da67d703ff0f0f561f779ec3d76b556b43a8e5c0be6837c975e1095c35f8"}],"sourceInfo":"acquired package info from go module information: /dashboard","licenseConcluded":"NOASSERTION","licenseDeclared":"NOASSERTION","copyrightText":"NOASSERTION","externalRefs":[{"referenceCategory":"SECURITY","referenceType":"cpe23Type","referenceLocator":"cpe:2.3:a:modern-go:concurrent:v0.0.0-20180306012644-bacd9c7ef1dd:*:*:*:*:*:*:*"},{"referenceCategory":"SECURITY","referenceType":"cpe23Type","referenceLocator":"cpe:2.3:a:modern_go:concurrent:v0.0.0-20180306012644-bacd9c7ef1dd:*:*:*:*:*:*:*"},{"referenceCategory":"SECURITY","referenceType":"cpe23Type","referenceLocator":"cpe:2.3:a:modern:concurrent:v0.0.0-20180306012644-bacd9c7ef1dd:*:*:*:*:*:*:*"},{"referenceCategory":"PACKAGE-MANAGER","referenceType":"purl","referenceLocator":"pkg:golang/github.com/modern-go/concurrent@v0.0.0-20180306012644-bacd9c7ef1dd"}]},{"name":"github.com/modern-go/reflect2","SPDXID":"SPDXRef-Package-go-module-github.com-modern-go-reflect2-3e6665b6a58a6817","versionInfo":"v1.0.1","supplier":"NOASSERTION","downloadLocation":"NOASSERTION","filesAnalyzed":false,"checksums":[{"algorithm":"SHA256","checksumValue":"f5fe35dacfba4666172d665213355580f18aec2d8fa611e3e5126bbdfc7d0162"}],"sourceInfo":"acquired package info from go module information: /dashboard","licenseConcluded":"NOASSERTION","licenseDeclared":"NOASSERTION","copyrightText":"NOASSERTION","externalRefs":[{"referenceCategory":"SECURITY","referenceType":"cpe23Type","referenceLocator":"cpe:2.3:a:modern-go:reflect2:v1.0.1:*:*:*:*:*:*:*"},{"referenceCategory":"SECURITY","referenceType":"cpe23Type","referenceLocator":"cpe:2.3:a:modern_go:reflect2:v1.0.1:*:*:*:*:*:*:*"},{"referenceCategory":"SECURITY","referenceType":"cpe23Type","referenceLocator":"cpe:2.3:a:modern:reflect2:v1.0.1:*:*:*:*:*:*:*"},{"referenceCategory":"PACKAGE-MANAGER","referenceType":"purl","referenceLocator":"pkg:golang/github.com/modern-go/reflect2@v1.0.1"}]},{"name":"github.com/opencontainers/go-digest","SPDXID":"SPDXRef-Package-go-module-github.com-opencontainers-go-digest-37ffb4fddbb19c56","versionInfo":"v1.0.0-rc1","supplier":"NOASSERTION","downloadLocation":"NOASSERTION","filesAnalyzed":false,"checksums":[{"algorithm":"SHA256","checksumValue":"5b389f5e13953843ae158389016e9a42a5b44e8a06da2922dc4dc88be58dee04"}],"sourceInfo":"acquired package info from go module information: /dashboard","licenseConcluded":"NOASSERTION","licenseDeclared":"NOASSERTION","copyrightText":"NOASSERTION","externalRefs":[{"referenceCategory":"SECURITY","referenceType":"cpe23Type","referenceLocator":"cpe:2.3:a:opencontainers:go-digest:v1.0.0-rc1:*:*:*:*:*:*:*"},{"referenceCategory":"SECURITY","referenceType":"cpe23Type","referenceLocator":"cpe:2.3:a:opencontainers:go_digest:v1.0.0-rc1:*:*:*:*:*:*:*"},{"referenceCategory":"PACKAGE-MANAGER","referenceType":"purl","referenceLocator":"pkg:golang/github.com/opencontainers/go-digest@v1.0.0-rc1"}]},{"name":"github.com/prometheus/client_golang","SPDXID":"SPDXRef-Package-go-module-github.com-prometheus-client-golang-d9d5cccd79247907","versionInfo":"v1.5.1","supplier":"NOASSERTION","downloadLocation":"NOASSERTION","filesAnalyzed":false,"checksums":[{"algorithm":"SHA256","checksumValue":"6dd1d889ec86947fba38b124d984216bc4c789bdf428fd3fc83d181fd9bac5c0"}],"sourceInfo":"acquired package info from go module information: /dashboard","licenseConcluded":"NOASSERTION","licenseDeclared":"NOASSERTION","copyrightText":"NOASSERTION","externalRefs":[{"referenceCategory":"SECURITY","referenceType":"cpe23Type","referenceLocator":"cpe:2.3:a:prometheus:client-golang:v1.5.1:*:*:*:*:*:*:*"},{"referenceCategory":"SECURITY","referenceType":"cpe23Type","referenceLocator":"cpe:2.3:a:prometheus:client_golang:v1.5.1:*:*:*:*:*:*:*"},{"referenceCategory":"PACKAGE-MANAGER","referenceType":"purl","referenceLocator":"pkg:golang/github.com/prometheus/client_golang@v1.5.1"}]},{"name":"github.com/prometheus/client_model","SPDXID":"SPDXRef-Package-go-module-github.com-prometheus-client-model-1cc48528c9f378da","versionInfo":"v0.2.0","supplier":"NOASSERTION","downloadLocation":"NOASSERTION","filesAnalyzed":false,"checksums":[{"algorithm":"SHA256","checksumValue":"baae61d1df86bb18972c92cd001320a76a945833e22ef802cf3d9d511fbf5bf3"}],"sourceInfo":"acquired package info from go module information: /dashboard","licenseConcluded":"NOASSERTION","licenseDeclared":"NOASSERTION","copyrightText":"NOASSERTION","externalRefs":[{"referenceCategory":"SECURITY","referenceType":"cpe23Type","referenceLocator":"cpe:2.3:a:prometheus:client-model:v0.2.0:*:*:*:*:*:*:*"},{"referenceCategory":"SECURITY","referenceType":"cpe23Type","referenceLocator":"cpe:2.3:a:prometheus:client_model:v0.2.0:*:*:*:*:*:*:*"},{"referenceCategory":"PACKAGE-MANAGER","referenceType":"purl","referenceLocator":"pkg:golang/github.com/prometheus/client_model@v0.2.0"}]},{"name":"github.com/prometheus/common","SPDXID":"SPDXRef-Package-go-module-github.com-prometheus-common-68ca758db5129334","versionInfo":"v0.9.1","supplier":"NOASSERTION","downloadLocation":"NOASSERTION","filesAnalyzed":false,"checksums":[{"algorithm":"SHA256","checksumValue":"28e32d376f2d95b6a6dffed928460a1e12a82596188f780c1f8b9ceb6c7b5fb5"}],"sourceInfo":"acquired package info from go module information: /dashboard","licenseConcluded":"NOASSERTION","licenseDeclared":"NOASSERTION","copyrightText":"NOASSERTION","externalRefs":[{"referenceCategory":"SECURITY","referenceType":"cpe23Type","referenceLocator":"cpe:2.3:a:prometheus:common:v0.9.1:*:*:*:*:*:*:*"},{"referenceCategory":"PACKAGE-MANAGER","referenceType":"purl","referenceLocator":"pkg:golang/github.com/prometheus/common@v0.9.1"}]},{"name":"github.com/prometheus/procfs","SPDXID":"SPDXRef-Package-go-module-github.com-prometheus-procfs-7b03b7443c165159","versionInfo":"v0.0.8","supplier":"NOASSERTION","downloadLocation":"NOASSERTION","filesAnalyzed":false,"checksums":[{"algorithm":"SHA256","checksumValue":"f9fa5665d4f6e292418aa25d0306018cf4a4fb962643360d3d8cd0b1dccb92df"}],"sourceInfo":"acquired package info from go module information: /dashboard","licenseConcluded":"NOASSERTION","licenseDeclared":"NOASSERTION","copyrightText":"NOASSERTION","externalRefs":[{"referenceCategory":"SECURITY","referenceType":"cpe23Type","referenceLocator":"cpe:2.3:a:prometheus:procfs:v0.0.8:*:*:*:*:*:*:*"},{"referenceCategory":"PACKAGE-MANAGER","referenceType":"purl","referenceLocator":"pkg:golang/github.com/prometheus/procfs@v0.0.8"}]},{"name":"github.com/spf13/pflag","SPDXID":"SPDXRef-Package-go-module-github.com-spf13-pflag-2b338bd868824f9b","versionInfo":"v1.0.5","supplier":"NOASSERTION","downloadLocation":"NOASSERTION","filesAnalyzed":false,"checksums":[{"algorithm":"SHA256","checksumValue":"8b2f951543823f56bef3216da3f76b836089e6ed3246807b7d9c370cabff2570"}],"sourceInfo":"acquired package info from go module information: /dashboard","licenseConcluded":"NOASSERTION","licenseDeclared":"NOASSERTION","copyrightText":"NOASSERTION","externalRefs":[{"referenceCategory":"SECURITY","referenceType":"cpe23Type","referenceLocator":"cpe:2.3:a:spf13:pflag:v1.0.5:*:*:*:*:*:*:*"},{"referenceCategory":"PACKAGE-MANAGER","referenceType":"purl","referenceLocator":"pkg:golang/github.com/spf13/pflag@v1.0.5"}]},{"name":"golang.org/x/crypto","SPDXID":"SPDXRef-Package-go-module-golang.org-x-crypto-8cb9c269664abfa1","versionInfo":"v0.0.0-20200220183623-bac4c82f6975","supplier":"NOASSERTION","downloadLocation":"NOASSERTION","filesAnalyzed":false,"checksums":[{"algorithm":"SHA256","checksumValue":"fd397ba47f786ef6c000705d6494fde3b33ffa0a74f82a905c3b4c442d1fb1ea"}],"sourceInfo":"acquired package info from go module information: /dashboard","licenseConcluded":"NOASSERTION","licenseDeclared":"NOASSERTION","copyrightText":"NOASSERTION","externalRefs":[{"referenceCategory":"SECURITY","referenceType":"cpe23Type","referenceLocator":"cpe:2.3:a:golang:x\\/crypto:v0.0.0-20200220183623-bac4c82f6975:*:*:*:*:*:*:*"},{"referenceCategory":"PACKAGE-MANAGER","referenceType":"purl","referenceLocator":"pkg:golang/golang.org/x/crypto@v0.0.0-20200220183623-bac4c82f6975"}]},{"name":"golang.org/x/net","SPDXID":"SPDXRef-Package-go-module-golang.org-x-net-cb0775e5cbfb9f56","versionInfo":"v0.0.0-20200324143707-d3edc9973b7e","supplier":"NOASSERTION","downloadLocation":"NOASSERTION","filesAnalyzed":false,"checksums":[{"algorithm":"SHA256","checksumValue":"dc6f9c5228e7ed70fe4b878915d769e773efefeb25ac44a99728c6db91e02fe9"}],"sourceInfo":"acquired package info from go module information: /dashboard","licenseConcluded":"NOASSERTION","licenseDeclared":"NOASSERTION","copyrightText":"NOASSERTION","externalRefs":[{"referenceCategory":"SECURITY","referenceType":"cpe23Type","referenceLocator":"cpe:2.3:a:golang:x\\/net:v0.0.0-20200324143707-d3edc9973b7e:*:*:*:*:*:*:*"},{"referenceCategory":"PACKAGE-MANAGER","referenceType":"purl","referenceLocator":"pkg:golang/golang.org/x/net@v0.0.0-20200324143707-d3edc9973b7e"}]},{"name":"golang.org/x/oauth2","SPDXID":"SPDXRef-Package-go-module-golang.org-x-oauth2-b59eabb15512630f","versionInfo":"v0.0.0-20190604053449-0f29369cfe45","supplier":"NOASSERTION","downloadLocation":"NOASSERTION","filesAnalyzed":false,"checksums":[{"algorithm":"SHA256","checksumValue":"495c1320068f0b653f02fbcb359d9aece56c981a42f0be419702b5c211f7866d"}],"sourceInfo":"acquired package info from go module information: /dashboard","licenseConcluded":"NOASSERTION","licenseDeclared":"NOASSERTION","copyrightText":"NOASSERTION","externalRefs":[{"referenceCategory":"SECURITY","referenceType":"cpe23Type","referenceLocator":"cpe:2.3:a:golang:x\\/oauth2:v0.0.0-20190604053449-0f29369cfe45:*:*:*:*:*:*:*"},{"referenceCategory":"PACKAGE-MANAGER","referenceType":"purl","referenceLocator":"pkg:golang/golang.org/x/oauth2@v0.0.0-20190604053449-0f29369cfe45"}]},{"name":"golang.org/x/sys","SPDXID":"SPDXRef-Package-go-module-golang.org-x-sys-5b38672248a6ca84","versionInfo":"v0.0.0-20200323222414-85ca7c5b95cd","supplier":"NOASSERTION","downloadLocation":"NOASSERTION","filesAnalyzed":false,"checksums":[{"algorithm":"SHA256","checksumValue":"c619b0caf8b3b93802daacfb665325b8fdb4b96f82dd19b4143fd62c35fcf3ce"}],"sourceInfo":"acquired package info from go module information: /dashboard","licenseConcluded":"NOASSERTION","licenseDeclared":"NOASSERTION","copyrightText":"NOASSERTION","externalRefs":[{"referenceCategory":"SECURITY","referenceType":"cpe23Type","referenceLocator":"cpe:2.3:a:golang:x\\/sys:v0.0.0-20200323222414-85ca7c5b95cd:*:*:*:*:*:*:*"},{"referenceCategory":"PACKAGE-MANAGER","referenceType":"purl","referenceLocator":"pkg:golang/golang.org/x/sys@v0.0.0-20200323222414-85ca7c5b95cd"}]},{"name":"golang.org/x/text","SPDXID":"SPDXRef-Package-go-module-golang.org-x-text-ded3b83b1065679a","versionInfo":"v0.3.2","supplier":"NOASSERTION","downloadLocation":"NOASSERTION","filesAnalyzed":false,"checksums":[{"algorithm":"SHA256","checksumValue":"b56d9b9a206ac20263fd4a6ab42f04a571195583b0534c86e2259ba6b49501cb"}],"sourceInfo":"acquired package info from go module information: /dashboard","licenseConcluded":"NOASSERTION","licenseDeclared":"NOASSERTION","copyrightText":"NOASSERTION","externalRefs":[{"referenceCategory":"SECURITY","referenceType":"cpe23Type","referenceLocator":"cpe:2.3:a:golang:x\\/text:v0.3.2:*:*:*:*:*:*:*"},{"referenceCategory":"PACKAGE-MANAGER","referenceType":"purl","referenceLocator":"pkg:golang/golang.org/x/text@v0.3.2"}]},{"name":"golang.org/x/time","SPDXID":"SPDXRef-Package-go-module-golang.org-x-time-7d8fc965713819a9","versionInfo":"v0.0.0-20190308202827-9d24e82272b4","supplier":"NOASSERTION","downloadLocation":"NOASSERTION","filesAnalyzed":false,"checksums":[{"algorithm":"SHA256","checksumValue":"4af1594fa8f2a9168e797a5ce61fc949f65e9c9d8edf7d1a06c7fb25f4945e64"}],"sourceInfo":"acquired package info from go module information: /dashboard","licenseConcluded":"NOASSERTION","licenseDeclared":"NOASSERTION","copyrightText":"NOASSERTION","externalRefs":[{"referenceCategory":"SECURITY","referenceType":"cpe23Type","referenceLocator":"cpe:2.3:a:golang:x\\/time:v0.0.0-20190308202827-9d24e82272b4:*:*:*:*:*:*:*"},{"referenceCategory":"PACKAGE-MANAGER","referenceType":"purl","referenceLocator":"pkg:golang/golang.org/x/time@v0.0.0-20190308202827-9d24e82272b4"}]},{"name":"gopkg.in/igm/sockjs-go.v2","SPDXID":"SPDXRef-Package-go-module-gopkg.in-igm-sockjs-go.v2-5070f86c7a6c0006","versionInfo":"v2.1.0","supplier":"NOASSERTION","downloadLocation":"NOASSERTION","filesAnalyzed":false,"checksums":[{"algorithm":"SHA256","checksumValue":"121ab29b19df924c22f11ed2648500467efb334b2503cbe48b456071f39d00bc"}],"sourceInfo":"acquired package info from go module information: /dashboard","licenseConcluded":"NOASSERTION","licenseDeclared":"NOASSERTION","copyrightText":"NOASSERTION","externalRefs":[{"referenceCategory":"PACKAGE-MANAGER","referenceType":"purl","referenceLocator":"pkg:golang/gopkg.in/igm/sockjs-go.v2@v2.1.0"}]},{"name":"gopkg.in/inf.v0","SPDXID":"SPDXRef-Package-go-module-gopkg.in-inf.v0-4fb7ee0718dd1ef1","versionInfo":"v0.9.1","supplier":"NOASSERTION","downloadLocation":"NOASSERTION","filesAnalyzed":false,"checksums":[{"algorithm":"SHA256","checksumValue":"ef73390a86728b764b30ec83950874df50b1e8df4d0c9d95bdf97be840c08037"}],"sourceInfo":"acquired package info from go module information: /dashboard","licenseConcluded":"NOASSERTION","licenseDeclared":"NOASSERTION","copyrightText":"NOASSERTION","externalRefs":[{"referenceCategory":"PACKAGE-MANAGER","referenceType":"purl","referenceLocator":"pkg:golang/gopkg.in/inf.v0@v0.9.1"}]},{"name":"gopkg.in/square/go-jose.v2","SPDXID":"SPDXRef-Package-go-module-gopkg.in-square-go-jose.v2-210a7d7c5a039f3f","versionInfo":"v2.4.1","supplier":"NOASSERTION","downloadLocation":"NOASSERTION","filesAnalyzed":false,"checksums":[{"algorithm":"SHA256","checksumValue":"1f44e62edeff2a6ce5ac33a96b517ecebd1393dd0f6c96017ec5549912eb7fd6"}],"sourceInfo":"acquired package info from go module information: /dashboard","licenseConcluded":"NOASSERTION","licenseDeclared":"NOASSERTION","copyrightText":"NOASSERTION","externalRefs":[{"referenceCategory":"PACKAGE-MANAGER","referenceType":"purl","referenceLocator":"pkg:golang/gopkg.in/square/go-jose.v2@v2.4.1"}]},{"name":"gopkg.in/yaml.v2","SPDXID":"SPDXRef-Package-go-module-gopkg.in-yaml.v2-5b54d1047e18300d","versionInfo":"v2.2.8","supplier":"NOASSERTION","downloadLocation":"NOASSERTION","filesAnalyzed":false,"checksums":[{"algorithm":"SHA256","checksumValue":"a1b37565a809494188d0493f2c19ae8f848d2cf7c89f2dcab0a168a7145d8f5d"}],"sourceInfo":"acquired package info from go module information: /dashboard","licenseConcluded":"NOASSERTION","licenseDeclared":"NOASSERTION","copyrightText":"NOASSERTION","externalRefs":[{"referenceCategory":"PACKAGE-MANAGER","referenceType":"purl","referenceLocator":"pkg:golang/gopkg.in/yaml.v2@v2.2.8"}]},{"name":"k8s.io/api","SPDXID":"SPDXRef-Package-go-module-k8s.io-api-c5a5dd299a138b48","versionInfo":"v0.18.2","supplier":"NOASSERTION","downloadLocation":"NOASSERTION","filesAnalyzed":false,"checksums":[{"algorithm":"SHA256","checksumValue":"c06e60e599925609b907e7873086c8f441804d2d8bf19ef6add6b5f51204818f"}],"sourceInfo":"acquired package info from go module information: /dashboard","licenseConcluded":"NOASSERTION","licenseDeclared":"NOASSERTION","copyrightText":"NOASSERTION","externalRefs":[{"referenceCategory":"PACKAGE-MANAGER","referenceType":"purl","referenceLocator":"pkg:golang/k8s.io/api@v0.18.2"}]},{"name":"k8s.io/apiextensions-apiserver","SPDXID":"SPDXRef-Package-go-module-k8s.io-apiextensions-apiserver-d6f7aba3748dfb4d","versionInfo":"v0.18.2","supplier":"NOASSERTION","downloadLocation":"NOASSERTION","filesAnalyzed":false,"checksums":[{"algorithm":"SHA256","checksumValue":"238bf7fe302e402fbcf4bdd9edd0e002237810e8cdeac6e6ea206a4301d36a1f"}],"sourceInfo":"acquired package info from go module information: /dashboard","licenseConcluded":"NOASSERTION","licenseDeclared":"NOASSERTION","copyrightText":"NOASSERTION","externalRefs":[{"referenceCategory":"PACKAGE-MANAGER","referenceType":"purl","referenceLocator":"pkg:golang/k8s.io/apiextensions-apiserver@v0.18.2"}]},{"name":"k8s.io/apimachinery","SPDXID":"SPDXRef-Package-go-module-k8s.io-apimachinery-12c77de988c65ee5","versionInfo":"v0.18.2","supplier":"NOASSERTION","downloadLocation":"NOASSERTION","filesAnalyzed":false,"checksums":[{"algorithm":"SHA256","checksumValue":"e380a6b5b9a4cd50c0842a5155288fd91e4f3eb0b646d948bff32807cc697510"}],"sourceInfo":"acquired package info from go module information: /dashboard","licenseConcluded":"NOASSERTION","licenseDeclared":"NOASSERTION","copyrightText":"NOASSERTION","externalRefs":[{"referenceCategory":"PACKAGE-MANAGER","referenceType":"purl","referenceLocator":"pkg:golang/k8s.io/apimachinery@v0.18.2"}]},{"name":"k8s.io/client-go","SPDXID":"SPDXRef-Package-go-module-k8s.io-client-go-0b2d3bfb1ecd10d5","versionInfo":"v0.18.2","supplier":"NOASSERTION","downloadLocation":"NOASSERTION","filesAnalyzed":false,"checksums":[{"algorithm":"SHA256","checksumValue":"68b07489a0f89e6c21edaad3db0227fa532702aeceb308da7a3910f29f5b0581"}],"sourceInfo":"acquired package info from go module information: /dashboard","licenseConcluded":"NOASSERTION","licenseDeclared":"NOASSERTION","copyrightText":"NOASSERTION","externalRefs":[{"referenceCategory":"PACKAGE-MANAGER","referenceType":"purl","referenceLocator":"pkg:golang/k8s.io/client-go@v0.18.2"}]},{"name":"k8s.io/heapster","SPDXID":"SPDXRef-Package-go-module-k8s.io-heapster-d33f785c8850246b","versionInfo":"v1.5.4","supplier":"NOASSERTION","downloadLocation":"NOASSERTION","filesAnalyzed":false,"checksums":[{"algorithm":"SHA256","checksumValue":"947d8609976a46650a0e8caa4608976d198871ebda3d84ef920b8eb98525f204"}],"sourceInfo":"acquired package info from go module information: /dashboard","licenseConcluded":"NOASSERTION","licenseDeclared":"NOASSERTION","copyrightText":"NOASSERTION","externalRefs":[{"referenceCategory":"PACKAGE-MANAGER","referenceType":"purl","referenceLocator":"pkg:golang/k8s.io/heapster@v1.5.4"}]},{"name":"k8s.io/klog","SPDXID":"SPDXRef-Package-go-module-k8s.io-klog-87b4cb3b728ddda0","versionInfo":"v1.0.0","supplier":"NOASSERTION","downloadLocation":"NOASSERTION","filesAnalyzed":false,"checksums":[{"algorithm":"SHA256","checksumValue":"3edfb28c5e5a075c434956dabb856c59ef9d40dcc0d2abf52e55dd0b6745e90f"}],"sourceInfo":"acquired package info from go module information: /dashboard","licenseConcluded":"NOASSERTION","licenseDeclared":"NOASSERTION","copyrightText":"NOASSERTION","externalRefs":[{"referenceCategory":"PACKAGE-MANAGER","referenceType":"purl","referenceLocator":"pkg:golang/k8s.io/klog@v1.0.0"}]},{"name":"k8s.io/utils","SPDXID":"SPDXRef-Package-go-module-k8s.io-utils-4c787088e7574e78","versionInfo":"v0.0.0-20200324210504-a9aa75ae1b89","supplier":"NOASSERTION","downloadLocation":"NOASSERTION","filesAnalyzed":false,"checksums":[{"algorithm":"SHA256","checksumValue":"778bd53a35e6ebcec5d622d23f6ab79723cfbb2bd352ddda5680698b60ea46c5"}],"sourceInfo":"acquired package info from go module information: /dashboard","licenseConcluded":"NOASSERTION","licenseDeclared":"NOASSERTION","copyrightText":"NOASSERTION","externalRefs":[{"referenceCategory":"PACKAGE-MANAGER","referenceType":"purl","referenceLocator":"pkg:golang/k8s.io/utils@v0.0.0-20200324210504-a9aa75ae1b89"}]},{"name":"sigs.k8s.io/structured-merge-diff/v3","SPDXID":"SPDXRef-Package-go-module-sigs.k8s.io-structured-merge-diff-v3-b49312cf5b027290","versionInfo":"v3.0.0","supplier":"NOASSERTION","downloadLocation":"NOASSERTION","filesAnalyzed":false,"checksums":[{"algorithm":"SHA256","checksumValue":"74e98864131f85c1d2d3d5d990cc94824ab9b6b837fe347225815952268ea7c1"}],"sourceInfo":"acquired package info from go module information: /dashboard","licenseConcluded":"NOASSERTION","licenseDeclared":"NOASSERTION","copyrightText":"NOASSERTION","externalRefs":[{"referenceCategory":"SECURITY","referenceType":"cpe23Type","referenceLocator":"cpe:2.3:a:structured-merge-diff:v3:v3.0.0:*:*:*:*:*:*:*"},{"referenceCategory":"SECURITY","referenceType":"cpe23Type","referenceLocator":"cpe:2.3:a:structured_merge_diff:v3:v3.0.0:*:*:*:*:*:*:*"},{"referenceCategory":"SECURITY","referenceType":"cpe23Type","referenceLocator":"cpe:2.3:a:structured-merge:v3:v3.0.0:*:*:*:*:*:*:*"},{"referenceCategory":"SECURITY","referenceType":"cpe23Type","referenceLocator":"cpe:2.3:a:structured_merge:v3:v3.0.0:*:*:*:*:*:*:*"},{"referenceCategory":"SECURITY","referenceType":"cpe23Type","referenceLocator":"cpe:2.3:a:structured:v3:v3.0.0:*:*:*:*:*:*:*"},{"referenceCategory":"PACKAGE-MANAGER","referenceType":"purl","referenceLocator":"pkg:golang/sigs.k8s.io/structured-merge-diff/v3@v3.0.0"}]},{"name":"sigs.k8s.io/yaml","SPDXID":"SPDXRef-Package-go-module-sigs.k8s.io-yaml-21533b2a98e27564","versionInfo":"v1.2.0","supplier":"NOASSERTION","downloadLocation":"NOASSERTION","filesAnalyzed":false,"checksums":[{"algorithm":"SHA256","checksumValue":"92bfcc09e1562564f0c9a1e847d73c1231fd3ae98e9a817d60689977b9459bf4"}],"sourceInfo":"acquired package info from go module information: /dashboard","licenseConcluded":"NOASSERTION","licenseDeclared":"NOASSERTION","copyrightText":"NOASSERTION","externalRefs":[{"referenceCategory":"PACKAGE-MANAGER","referenceType":"purl","referenceLocator":"pkg:golang/sigs.k8s.io/yaml@v1.2.0"}]},{"name":"stdlib","SPDXID":"SPDXRef-Package-go-module-stdlib-e008a5027d5e90e4","versionInfo":"go1.13.9","supplier":"NOASSERTION","downloadLocation":"NOASSERTION","filesAnalyzed":false,"sourceInfo":"acquired package info from go module information: /dashboard","licenseConcluded":"NOASSERTION","licenseDeclared":"BSD-3-Clause","copyrightText":"NOASSERTION","externalRefs":[{"referenceCategory":"SECURITY","referenceType":"cpe23Type","referenceLocator":"cpe:2.3:a:golang:go:1.13.9:-:*:*:*:*:*:*"},{"referenceCategory":"PACKAGE-MANAGER","referenceType":"purl","referenceLocator":"pkg:golang/stdlib@1.13.9"}]},{"name":"docker.io/kubernetesui/dashboard","SPDXID":"SPDXRef-DocumentRoot-Image-docker.io-kubernetesui-dashboard","versionInfo":"sha256:19207cca570f61bce2294595a767b51b4d7e1f223a003c7972c350cf8689f49e","supplier":"NOASSERTION","downloadLocation":"NOASSERTION","filesAnalyzed":false,"checksums":[{"algorithm":"SHA256","checksumValue":"19207cca570f61bce2294595a767b51b4d7e1f223a003c7972c350cf8689f49e"}],"externalRefs":[{"referenceCategory":"PACKAGE-MANAGER","referenceType":"purl","referenceLocator":"pkg:oci/docker.io/kubernetesui/dashboard@sha256:19207cca570f61bce2294595a767b51b4d7e1f223a003c7972c350cf8689f49e?arch=arm64"}],"primaryPackagePurpose":"CONTAINER"}],"files":[{"fileName":"/dashboard","SPDXID":"SPDXRef-File-dashboard-38443aa546472e51","checksums":[{"algorithm":"SHA1","checksumValue":"0000000000000000000000000000000000000000"}],"licenseConcluded":"NOASSERTION","copyrightText":"","comment":"layerID: sha256:f7b4ad255e96af11556ad6418f7d89a22ff2e82aef678d3781544094774a166e"}],"relationships":[{"spdxElementId":"SPDXRef-Package-go-module-github.com-docker-distribution-08b5a9a351ef53c0","relatedSpdxElement":"SPDXRef-File-dashboard-38443aa546472e51","relationshipType":"OTHER","comment":"evident-by: indicates the package's existence is evident by the given file"},{"spdxElementId":"SPDXRef-Package-go-module-k8s.io-client-go-0b2d3bfb1ecd10d5","relatedSpdxElement":"SPDXRef-File-dashboard-38443aa546472e51","relationshipType":"OTHER","comment":"evident-by: indicates the package's existence is evident by the given file"},{"spdxElementId":"SPDXRef-Package-go-module-github.com-gogo-protobuf-0b988da356741366","relatedSpdxElement":"SPDXRef-File-dashboard-38443aa546472e51","relationshipType":"OTHER","comment":"evident-by: indicates the package's existence is evident by the given file"},{"spdxElementId":"SPDXRef-Package-go-module-github.com-golang-protobuf-0cffbb7042aa4592","relatedSpdxElement":"SPDXRef-File-dashboard-38443aa546472e51","relationshipType":"OTHER","comment":"evident-by: indicates the package's existence is evident by the given file"},{"spdxElementId":"SPDXRef-Package-go-module-github.com-gorilla-websocket-0ea3d3cfdb811e0e","relatedSpdxElement":"SPDXRef-File-dashboard-38443aa546472e51","relationshipType":"OTHER","comment":"evident-by: indicates the package's existence is evident by the given file"},{"spdxElementId":"SPDXRef-Package-go-module-github.com-kubernetes-dashboard-1280d10a0c0f61e1","relatedSpdxElement":"SPDXRef-File-dashboard-38443aa546472e51","relationshipType":"OTHER","comment":"evident-by: indicates the package's existence is evident by the given file"},{"spdxElementId":"SPDXRef-Package-go-module-k8s.io-apimachinery-12c77de988c65ee5","relatedSpdxElement":"SPDXRef-File-dashboard-38443aa546472e51","relationshipType":"OTHER","comment":"evident-by: indicates the package's existence is evident by the given file"},{"spdxElementId":"SPDXRef-Package-go-module-github.com-prometheus-client-model-1cc48528c9f378da","relatedSpdxElement":"SPDXRef-File-dashboard-38443aa546472e51","relationshipType":"OTHER","comment":"evident-by: indicates the package's existence is evident by the given file"},{"spdxElementId":"SPDXRef-Package-go-module-github.com-matttproud-golang-protobuf-extensions-1e24a08697e46313","relatedSpdxElement":"SPDXRef-File-dashboard-38443aa546472e51","relationshipType":"OTHER","comment":"evident-by: indicates the package's existence is evident by the given file"},{"spdxElementId":"SPDXRef-Package-go-module-gopkg.in-square-go-jose.v2-210a7d7c5a039f3f","relatedSpdxElement":"SPDXRef-File-dashboard-38443aa546472e51","relationshipType":"OTHER","comment":"evident-by: indicates the package's existence is evident by the given file"},{"spdxElementId":"SPDXRef-Package-go-module-sigs.k8s.io-yaml-21533b2a98e27564","relatedSpdxElement":"SPDXRef-File-dashboard-38443aa546472e51","relationshipType":"OTHER","comment":"evident-by: indicates the package's existence is evident by the given file"},{"spdxElementId":"SPDXRef-Package-go-module-github.com-spf13-pflag-2b338bd868824f9b","relatedSpdxElement":"SPDXRef-File-dashboard-38443aa546472e51","relationshipType":"OTHER","comment":"evident-by: indicates the package's existence is evident by the given file"},{"spdxElementId":"SPDXRef-Package-go-module-github.com-googleapis-gnostic-2db142b4066eaacc","relatedSpdxElement":"SPDXRef-File-dashboard-38443aa546472e51","relationshipType":"OTHER","comment":"evident-by: indicates the package's existence is evident by the given file"},{"spdxElementId":"SPDXRef-Package-go-module-github.com-opencontainers-go-digest-37ffb4fddbb19c56","relatedSpdxElement":"SPDXRef-File-dashboard-38443aa546472e51","relationshipType":"OTHER","comment":"evident-by: indicates the package's existence is evident by the given file"},{"spdxElementId":"SPDXRef-Package-go-module-github.com-beorn7-perks-3d9f6f257e59912c","relatedSpdxElement":"SPDXRef-File-dashboard-38443aa546472e51","relationshipType":"OTHER","comment":"evident-by: indicates the package's existence is evident by the given file"},{"spdxElementId":"SPDXRef-Package-go-module-github.com-modern-go-reflect2-3e6665b6a58a6817","relatedSpdxElement":"SPDXRef-File-dashboard-38443aa546472e51","relationshipType":"OTHER","comment":"evident-by: indicates the package's existence is evident by the given file"},{"spdxElementId":"SPDXRef-Package-go-module-github.com-modern-go-concurrent-438bdbeb24c38e6b","relatedSpdxElement":"SPDXRef-File-dashboard-38443aa546472e51","relationshipType":"OTHER","comment":"evident-by: indicates the package's existence is evident by the given file"},{"spdxElementId":"SPDXRef-Package-go-module-k8s.io-utils-4c787088e7574e78","relatedSpdxElement":"SPDXRef-File-dashboard-38443aa546472e51","relationshipType":"OTHER","comment":"evident-by: indicates the package's existence is evident by the given file"},{"spdxElementId":"SPDXRef-Package-go-module-gopkg.in-inf.v0-4fb7ee0718dd1ef1","relatedSpdxElement":"SPDXRef-File-dashboard-38443aa546472e51","relationshipType":"OTHER","comment":"evident-by: indicates the package's existence is evident by the given file"},{"spdxElementId":"SPDXRef-Package-go-module-gopkg.in-igm-sockjs-go.v2-5070f86c7a6c0006","relatedSpdxElement":"SPDXRef-File-dashboard-38443aa546472e51","relationshipType":"OTHER","comment":"evident-by: indicates the package's existence is evident by the given file"},{"spdxElementId":"SPDXRef-Package-go-module-golang.org-x-sys-5b38672248a6ca84","relatedSpdxElement":"SPDXRef-File-dashboard-38443aa546472e51","relationshipType":"OTHER","comment":"evident-by: indicates the package's existence is evident by the given file"},{"spdxElementId":"SPDXRef-Package-go-module-gopkg.in-yaml.v2-5b54d1047e18300d","relatedSpdxElement":"SPDXRef-File-dashboard-38443aa546472e51","relationshipType":"OTHER","comment":"evident-by: indicates the package's existence is evident by the given file"},{"spdxElementId":"SPDXRef-Package-go-module-github.com-imdario-mergo-650e120315a0b2da","relatedSpdxElement":"SPDXRef-File-dashboard-38443aa546472e51","relationshipType":"OTHER","comment":"evident-by: indicates the package's existence is evident by the given file"},{"spdxElementId":"SPDXRef-Package-go-module-github.com-prometheus-common-68ca758db5129334","relatedSpdxElement":"SPDXRef-File-dashboard-38443aa546472e51","relationshipType":"OTHER","comment":"evident-by: indicates the package's existence is evident by the given file"},{"spdxElementId":"SPDXRef-Package-go-module-github.com-google-gofuzz-6c878f23d3b6aa66","relatedSpdxElement":"SPDXRef-File-dashboard-38443aa546472e51","relationshipType":"OTHER","comment":"evident-by: indicates the package's existence is evident by the given file"},{"spdxElementId":"SPDXRef-Package-go-module-github.com-cespare-xxhash-v2-72545ddab7a1cb26","relatedSpdxElement":"SPDXRef-File-dashboard-38443aa546472e51","relationshipType":"OTHER","comment":"evident-by: indicates the package's existence is evident by the given file"},{"spdxElementId":"SPDXRef-Package-go-module-github.com-davecgh-go-spew-7641503dc0c87d5c","relatedSpdxElement":"SPDXRef-File-dashboard-38443aa546472e51","relationshipType":"OTHER","comment":"evident-by: indicates the package's existence is evident by the given file"},{"spdxElementId":"SPDXRef-Package-go-module-github.com-prometheus-procfs-7b03b7443c165159","relatedSpdxElement":"SPDXRef-File-dashboard-38443aa546472e51","relationshipType":"OTHER","comment":"evident-by: indicates the package's existence is evident by the given file"},{"spdxElementId":"SPDXRef-Package-go-module-golang.org-x-time-7d8fc965713819a9","relatedSpdxElement":"SPDXRef-File-dashboard-38443aa546472e51","relationshipType":"OTHER","comment":"evident-by: indicates the package's existence is evident by the given file"},{"spdxElementId":"SPDXRef-Package-go-module-k8s.io-klog-87b4cb3b728ddda0","relatedSpdxElement":"SPDXRef-File-dashboard-38443aa546472e51","relationshipType":"OTHER","comment":"evident-by: indicates the package's existence is evident by the given file"},{"spdxElementId":"SPDXRef-Package-go-module-github.com-emicklei-go-restful-89713c2a779036a7","relatedSpdxElement":"SPDXRef-File-dashboard-38443aa546472e51","relationshipType":"OTHER","comment":"evident-by: indicates the package's existence is evident by the given file"},{"spdxElementId":"SPDXRef-Package-go-module-golang.org-x-crypto-8cb9c269664abfa1","relatedSpdxElement":"SPDXRef-File-dashboard-38443aa546472e51","relationshipType":"OTHER","comment":"evident-by: indicates the package's existence is evident by the given file"},{"spdxElementId":"SPDXRef-Package-go-module-github.com-golang-glog-aa6ac801d47e0a1a","relatedSpdxElement":"SPDXRef-File-dashboard-38443aa546472e51","relationshipType":"OTHER","comment":"evident-by: indicates the package's existence is evident by the given file"},{"spdxElementId":"SPDXRef-Package-go-module-github.com-docker-spdystream-ae62e3f8dd60d9f2","relatedSpdxElement":"SPDXRef-File-dashboard-38443aa546472e51","relationshipType":"OTHER","comment":"evident-by: indicates the package's existence is evident by the given file"},{"spdxElementId":"SPDXRef-Package-go-module-sigs.k8s.io-structured-merge-diff-v3-b49312cf5b027290","relatedSpdxElement":"SPDXRef-File-dashboard-38443aa546472e51","relationshipType":"OTHER","comment":"evident-by: indicates the package's existence is evident by the given file"},{"spdxElementId":"SPDXRef-Package-go-module-golang.org-x-oauth2-b59eabb15512630f","relatedSpdxElement":"SPDXRef-File-dashboard-38443aa546472e51","relationshipType":"OTHER","comment":"evident-by: indicates the package's existence is evident by the given file"},{"spdxElementId":"SPDXRef-Package-go-module-k8s.io-api-c5a5dd299a138b48","relatedSpdxElement":"SPDXRef-File-dashboard-38443aa546472e51","relationshipType":"OTHER","comment":"evident-by: indicates the package's existence is evident by the given file"},{"spdxElementId":"SPDXRef-Package-go-module-golang.org-x-net-cb0775e5cbfb9f56","relatedSpdxElement":"SPDXRef-File-dashboard-38443aa546472e51","relationshipType":"OTHER","comment":"evident-by: indicates the package's existence is evident by the given file"},{"spdxElementId":"SPDXRef-Package-go-module-k8s.io-heapster-d33f785c8850246b","relatedSpdxElement":"SPDXRef-File-dashboard-38443aa546472e51","relationshipType":"OTHER","comment":"evident-by: indicates the package's existence is evident by the given file"},{"spdxElementId":"SPDXRef-Package-go-module-k8s.io-apiextensions-apiserver-d6f7aba3748dfb4d","relatedSpdxElement":"SPDXRef-File-dashboard-38443aa546472e51","relationshipType":"OTHER","comment":"evident-by: indicates the package's existence is evident by the given file"},{"spdxElementId":"SPDXRef-Package-go-module-github.com-prometheus-client-golang-d9d5cccd79247907","relatedSpdxElement":"SPDXRef-File-dashboard-38443aa546472e51","relationshipType":"OTHER","comment":"evident-by: indicates the package's existence is evident by the given file"},{"spdxElementId":"SPDXRef-Package-go-module-golang.org-x-text-ded3b83b1065679a","relatedSpdxElement":"SPDXRef-File-dashboard-38443aa546472e51","relationshipType":"OTHER","comment":"evident-by: indicates the package's existence is evident by the given file"},{"spdxElementId":"SPDXRef-Package-go-module-stdlib-e008a5027d5e90e4","relatedSpdxElement":"SPDXRef-File-dashboard-38443aa546472e51","relationshipType":"OTHER","comment":"evident-by: indicates the package's existence is evident by the given file"},{"spdxElementId":"SPDXRef-Package-go-module-github.com-json-iterator-go-fe9da05f02e8c280","relatedSpdxElement":"SPDXRef-File-dashboard-38443aa546472e51","relationshipType":"OTHER","comment":"evident-by: indicates the package's existence is evident by the given file"},{"spdxElementId":"SPDXRef-DocumentRoot-Image-docker.io-kubernetesui-dashboard","relatedSpdxElement":"SPDXRef-Package-go-module-github.com-beorn7-perks-3d9f6f257e59912c","relationshipType":"CONTAINS"},{"spdxElementId":"SPDXRef-DocumentRoot-Image-docker.io-kubernetesui-dashboard","relatedSpdxElement":"SPDXRef-Package-go-module-github.com-cespare-xxhash-v2-72545ddab7a1cb26","relationshipType":"CONTAINS"},{"spdxElementId":"SPDXRef-DocumentRoot-Image-docker.io-kubernetesui-dashboard","relatedSpdxElement":"SPDXRef-Package-go-module-github.com-davecgh-go-spew-7641503dc0c87d5c","relationshipType":"CONTAINS"},{"spdxElementId":"SPDXRef-DocumentRoot-Image-docker.io-kubernetesui-dashboard","relatedSpdxElement":"SPDXRef-Package-go-module-github.com-docker-distribution-08b5a9a351ef53c0","relationshipType":"CONTAINS"},{"spdxElementId":"SPDXRef-DocumentRoot-Image-docker.io-kubernetesui-dashboard","relatedSpdxElement":"SPDXRef-Package-go-module-github.com-docker-spdystream-ae62e3f8dd60d9f2","relationshipType":"CONTAINS"},{"spdxElementId":"SPDXRef-DocumentRoot-Image-docker.io-kubernetesui-dashboard","relatedSpdxElement":"SPDXRef-Package-go-module-github.com-emicklei-go-restful-89713c2a779036a7","relationshipType":"CONTAINS"},{"spdxElementId":"SPDXRef-DocumentRoot-Image-docker.io-kubernetesui-dashboard","relatedSpdxElement":"SPDXRef-Package-go-module-github.com-gogo-protobuf-0b988da356741366","relationshipType":"CONTAINS"},{"spdxElementId":"SPDXRef-DocumentRoot-Image-docker.io-kubernetesui-dashboard","relatedSpdxElement":"SPDXRef-Package-go-module-github.com-golang-glog-aa6ac801d47e0a1a","relationshipType":"CONTAINS"},{"spdxElementId":"SPDXRef-DocumentRoot-Image-docker.io-kubernetesui-dashboard","relatedSpdxElement":"SPDXRef-Package-go-module-github.com-golang-protobuf-0cffbb7042aa4592","relationshipType":"CONTAINS"},{"spdxElementId":"SPDXRef-DocumentRoot-Image-docker.io-kubernetesui-dashboard","relatedSpdxElement":"SPDXRef-Package-go-module-github.com-google-gofuzz-6c878f23d3b6aa66","relationshipType":"CONTAINS"},{"spdxElementId":"SPDXRef-DocumentRoot-Image-docker.io-kubernetesui-dashboard","relatedSpdxElement":"SPDXRef-Package-go-module-github.com-googleapis-gnostic-2db142b4066eaacc","relationshipType":"CONTAINS"},{"spdxElementId":"SPDXRef-DocumentRoot-Image-docker.io-kubernetesui-dashboard","relatedSpdxElement":"SPDXRef-Package-go-module-github.com-gorilla-websocket-0ea3d3cfdb811e0e","relationshipType":"CONTAINS"},{"spdxElementId":"SPDXRef-DocumentRoot-Image-docker.io-kubernetesui-dashboard","relatedSpdxElement":"SPDXRef-Package-go-module-github.com-imdario-mergo-650e120315a0b2da","relationshipType":"CONTAINS"},{"spdxElementId":"SPDXRef-DocumentRoot-Image-docker.io-kubernetesui-dashboard","relatedSpdxElement":"SPDXRef-Package-go-module-github.com-json-iterator-go-fe9da05f02e8c280","relationshipType":"CONTAINS"},{"spdxElementId":"SPDXRef-DocumentRoot-Image-docker.io-kubernetesui-dashboard","relatedSpdxElement":"SPDXRef-Package-go-module-github.com-kubernetes-dashboard-1280d10a0c0f61e1","relationshipType":"CONTAINS"},{"spdxElementId":"SPDXRef-DocumentRoot-Image-docker.io-kubernetesui-dashboard","relatedSpdxElement":"SPDXRef-Package-go-module-github.com-matttproud-golang-protobuf-extensions-1e24a08697e46313","relationshipType":"CONTAINS"},{"spdxElementId":"SPDXRef-DocumentRoot-Image-docker.io-kubernetesui-dashboard","relatedSpdxElement":"SPDXRef-Package-go-module-github.com-modern-go-concurrent-438bdbeb24c38e6b","relationshipType":"CONTAINS"},{"spdxElementId":"SPDXRef-DocumentRoot-Image-docker.io-kubernetesui-dashboard","relatedSpdxElement":"SPDXRef-Package-go-module-github.com-modern-go-reflect2-3e6665b6a58a6817","relationshipType":"CONTAINS"},{"spdxElementId":"SPDXRef-DocumentRoot-Image-docker.io-kubernetesui-dashboard","relatedSpdxElement":"SPDXRef-Package-go-module-github.com-opencontainers-go-digest-37ffb4fddbb19c56","relationshipType":"CONTAINS"},{"spdxElementId":"SPDXRef-DocumentRoot-Image-docker.io-kubernetesui-dashboard","relatedSpdxElement":"SPDXRef-Package-go-module-github.com-prometheus-client-golang-d9d5cccd79247907","relationshipType":"CONTAINS"},{"spdxElementId":"SPDXRef-DocumentRoot-Image-docker.io-kubernetesui-dashboard","relatedSpdxElement":"SPDXRef-Package-go-module-github.com-prometheus-client-model-1cc48528c9f378da","relationshipType":"CONTAINS"},{"spdxElementId":"SPDXRef-DocumentRoot-Image-docker.io-kubernetesui-dashboard","relatedSpdxElement":"SPDXRef-Package-go-module-github.com-prometheus-common-68ca758db5129334","relationshipType":"CONTAINS"},{"spdxElementId":"SPDXRef-DocumentRoot-Image-docker.io-kubernetesui-dashboard","relatedSpdxElement":"SPDXRef-Package-go-module-github.com-prometheus-procfs-7b03b7443c165159","relationshipType":"CONTAINS"},{"spdxElementId":"SPDXRef-DocumentRoot-Image-docker.io-kubernetesui-dashboard","relatedSpdxElement":"SPDXRef-Package-go-module-github.com-spf13-pflag-2b338bd868824f9b","relationshipType":"CONTAINS"},{"spdxElementId":"SPDXRef-DocumentRoot-Image-docker.io-kubernetesui-dashboard","relatedSpdxElement":"SPDXRef-Package-go-module-golang.org-x-crypto-8cb9c269664abfa1","relationshipType":"CONTAINS"},{"spdxElementId":"SPDXRef-DocumentRoot-Image-docker.io-kubernetesui-dashboard","relatedSpdxElement":"SPDXRef-Package-go-module-golang.org-x-net-cb0775e5cbfb9f56","relationshipType":"CONTAINS"},{"spdxElementId":"SPDXRef-DocumentRoot-Image-docker.io-kubernetesui-dashboard","relatedSpdxElement":"SPDXRef-Package-go-module-golang.org-x-oauth2-b59eabb15512630f","relationshipType":"CONTAINS"},{"spdxElementId":"SPDXRef-DocumentRoot-Image-docker.io-kubernetesui-dashboard","relatedSpdxElement":"SPDXRef-Package-go-module-golang.org-x-sys-5b38672248a6ca84","relationshipType":"CONTAINS"},{"spdxElementId":"SPDXRef-DocumentRoot-Image-docker.io-kubernetesui-dashboard","relatedSpdxElement":"SPDXRef-Package-go-module-golang.org-x-text-ded3b83b1065679a","relationshipType":"CONTAINS"},{"spdxElementId":"SPDXRef-DocumentRoot-Image-docker.io-kubernetesui-dashboard","relatedSpdxElement":"SPDXRef-Package-go-module-golang.org-x-time-7d8fc965713819a9","relationshipType":"CONTAINS"},{"spdxElementId":"SPDXRef-DocumentRoot-Image-docker.io-kubernetesui-dashboard","relatedSpdxElement":"SPDXRef-Package-go-module-gopkg.in-igm-sockjs-go.v2-5070f86c7a6c0006","relationshipType":"CONTAINS"},{"spdxElementId":"SPDXRef-DocumentRoot-Image-docker.io-kubernetesui-dashboard","relatedSpdxElement":"SPDXRef-Package-go-module-gopkg.in-inf.v0-4fb7ee0718dd1ef1","relationshipType":"CONTAINS"},{"spdxElementId":"SPDXRef-DocumentRoot-Image-docker.io-kubernetesui-dashboard","relatedSpdxElement":"SPDXRef-Package-go-module-gopkg.in-square-go-jose.v2-210a7d7c5a039f3f","relationshipType":"CONTAINS"},{"spdxElementId":"SPDXRef-DocumentRoot-Image-docker.io-kubernetesui-dashboard","relatedSpdxElement":"SPDXRef-Package-go-module-gopkg.in-yaml.v2-5b54d1047e18300d","relationshipType":"CONTAINS"},{"spdxElementId":"SPDXRef-DocumentRoot-Image-docker.io-kubernetesui-dashboard","relatedSpdxElement":"SPDXRef-Package-go-module-k8s.io-api-c5a5dd299a138b48","relationshipType":"CONTAINS"},{"spdxElementId":"SPDXRef-DocumentRoot-Image-docker.io-kubernetesui-dashboard","relatedSpdxElement":"SPDXRef-Package-go-module-k8s.io-apiextensions-apiserver-d6f7aba3748dfb4d","relationshipType":"CONTAINS"},{"spdxElementId":"SPDXRef-DocumentRoot-Image-docker.io-kubernetesui-dashboard","relatedSpdxElement":"SPDXRef-Package-go-module-k8s.io-apimachinery-12c77de988c65ee5","relationshipType":"CONTAINS"},{"spdxElementId":"SPDXRef-DocumentRoot-Image-docker.io-kubernetesui-dashboard","relatedSpdxElement":"SPDXRef-Package-go-module-k8s.io-client-go-0b2d3bfb1ecd10d5","relationshipType":"CONTAINS"},{"spdxElementId":"SPDXRef-DocumentRoot-Image-docker.io-kubernetesui-dashboard","relatedSpdxElement":"SPDXRef-Package-go-module-k8s.io-heapster-d33f785c8850246b","relationshipType":"CONTAINS"},{"spdxElementId":"SPDXRef-DocumentRoot-Image-docker.io-kubernetesui-dashboard","relatedSpdxElement":"SPDXRef-Package-go-module-k8s.io-klog-87b4cb3b728ddda0","relationshipType":"CONTAINS"},{"spdxElementId":"SPDXRef-DocumentRoot-Image-docker.io-kubernetesui-dashboard","relatedSpdxElement":"SPDXRef-Package-go-module-k8s.io-utils-4c787088e7574e78","relationshipType":"CONTAINS"},{"spdxElementId":"SPDXRef-DocumentRoot-Image-docker.io-kubernetesui-dashboard","relatedSpdxElement":"SPDXRef-Package-go-module-sigs.k8s.io-structured-merge-diff-v3-b49312cf5b027290","relationshipType":"CONTAINS"},{"spdxElementId":"SPDXRef-DocumentRoot-Image-docker.io-kubernetesui-dashboard","relatedSpdxElement":"SPDXRef-Package-go-module-sigs.k8s.io-yaml-21533b2a98e27564","relationshipType":"CONTAINS"},{"spdxElementId":"SPDXRef-DocumentRoot-Image-docker.io-kubernetesui-dashboard","relatedSpdxElement":"SPDXRef-Package-go-module-stdlib-e008a5027d5e90e4","relationshipType":"CONTAINS"},{"spdxElementId":"SPDXRef-DOCUMENT","relatedSpdxElement":"SPDXRef-DocumentRoot-Image-docker.io-kubernetesui-dashboard","relationshipType":"DESCRIBES"}]}
